quantum_inferno/__init__.py
quantum_inferno/cwt_atoms.py
quantum_inferno/scales_dyadic.py
quantum_inferno/styx_cwt.py
quantum_inferno/styx_fft.py
quantum_inferno/styx_stx.py
quantum_inferno/tfr_info.py
quantum_inferno/plot_templates/__init__.py
quantum_inferno/plot_templates/figure_attributes.py
quantum_inferno/plot_templates/plot_base.py
quantum_inferno/plot_templates/plot_templates.py
quantum_inferno/plot_templates/plot_templates_examples.py
quantum_inferno/plot_templates/quick_plots.py
quantum_inferno/synth/__init__.py
quantum_inferno/synth/benchmark_signal_demo.py
quantum_inferno/synth/benchmark_signals.py
quantum_inferno/synth/blast_gt_pulse.py
quantum_inferno/synth/doppler.py
quantum_inferno/synth/synthetic_signals.py
quantum_inferno/tests/__init__.py
quantum_inferno/tests/test_scales_dyadic.py
quantum_inferno/tests/plot_templates/__init__.py
quantum_inferno/tests/plot_templates/test_charts.py
quantum_inferno/tests/plot_templates/test_figure_attributes.py
quantum_inferno/tests/plot_templates/test_plot_base.py
quantum_inferno/tests/plot_templates/test_plot_templates.py
quantum_inferno/tests/synth/__init__.py
quantum_inferno/tests/synth/test_benchmarks.py
quantum_inferno/tests/synth/test_blast_gt_pulse.py
quantum_inferno/tests/synth/test_doppler.py
quantum_inferno/tests/synth/test_synthetics.py
quantum_inferno/tests/utilities/test_calculations.py
quantum_inferno/tests/utilities/test_date_time.py
quantum_inferno/tests/utilities/test_frequency_scales.py
quantum_inferno/tests/utilities/test_matrix.py
quantum_inferno/tests/utilities/test_picker.py
quantum_inferno/tests/utilities/test_rescaling.py
quantum_inferno/tests/utilities/test_sampling.py
quantum_inferno/tests/utilities/test_short_time_fft.py
quantum_inferno/tests/utilities/test_window.py
quantum_inferno/utilities/calculations.py
quantum_inferno/utilities/date_time.py
quantum_inferno/utilities/exporting.py
quantum_inferno/utilities/frequency_scales.py
quantum_inferno/utilities/matrix.py
quantum_inferno-1.1.3.dist-info/LICENSE
quantum_inferno-1.1.3.dist-info/METADATA
quantum_inferno-1.1.3.dist-info/WHEEL
quantum_inferno-1.1.3.dist-info/top_level.txt
quantum_inferno-1.1.3.dist-info/RECORD
