Metadata-Version: 2.2
Name: quantum_inferno
Version: 1.1.3
Summary: Quantized Information Entropy, Nth Octave (INFERNO)
Author-email: "ISLA, UH" <milton@isla.hawaii.edu>
License: MIT License
Project-URL: homepage, https://github.com/ISLA-UH/quantum-inferno.git
Project-URL: PyPI, https://pypi.org/project/quantum-inferno/
Requires-Python: <=3.14,>=3.9
License-File: LICENSE
Requires-Dist: matplotlib>=3.10.0
Requires-Dist: numpy>=2.2.1
Requires-Dist: scipy>=1.15.0
Requires-Dist: setuptools>=75.7.0
